mlrl/__init__.py
mlrl/testbed_arff/__init__.py
mlrl/testbed_arff/experiments/__init__.py
mlrl/testbed_arff/experiments/input/__init__.py
mlrl/testbed_arff/experiments/input/sources/__init__.py
mlrl/testbed_arff/experiments/input/sources/source_arff.py
mlrl/testbed_arff/experiments/output/__init__.py
mlrl/testbed_arff/experiments/output/sinks/__init__.py
mlrl/testbed_arff/experiments/output/sinks/sink_arff.py
mlrl_testbed_arff-0.15.1.dist-info/METADATA
mlrl_testbed_arff-0.15.1.dist-info/WHEEL
mlrl_testbed_arff-0.15.1.dist-info/top_level.txt
mlrl_testbed_arff-0.15.1.dist-info/RECORD
