Metadata-Version: 2.4
Name: mlrl-testbed-arff
Version: 0.15.1
Summary: Adds support for ARFF files to the package "mlrl-testbed"
Author-email: Michael Rapp <michael.rapp.ml@gmail.com>
License-Expression: MIT
Project-URL: homepage, https://github.com/mrapp-ke/MLRL-Boomer
Project-URL: source, https://github.com/mrapp-ke/MLRL-Boomer.git
Project-URL: download, https://github.com/mrapp-ke/MLRL-Boomer/releases
Project-URL: changelog, https://raw.githubusercontent.com/mrapp-ke/MLRL-Boomer/refs/heads/main/CHANGELOG.md
Project-URL: documentation, https://mlrl-boomer.readthedocs.io/en/latest
Project-URL: issues, https://github.com/mrapp-ke/MLRL-Boomer/issues
Keywords: arff,machine learning
Classifier: Development Status :: 5 - Production/Stable
Classifier: Intended Audience :: Science/Research
Classifier: Operating System :: OS Independent
Classifier: Programming Language :: Python :: 3
Classifier: Topic :: Scientific/Engineering :: Artificial Intelligence
Classifier: Topic :: Software Development :: Libraries :: Python Modules
Requires-Python: >=3.12
Requires-Dist: liac-arff<2.6,>=2.5
Requires-Dist: mlrl-testbed-sklearn==0.15.1
